pykilosort/__init__.py
pykilosort/cluster.py
pykilosort/cptools.py
pykilosort/datashift2.py
pykilosort/event.py
pykilosort/ibl.py
pykilosort/learn.py
pykilosort/main.py
pykilosort/params.py
pykilosort/postprocess.py
pykilosort/preprocess.py
pykilosort/qc.py
pykilosort/utils.py
pykilosort/io/__init__.py
pykilosort/io/probes.py
pykilosort-1.4.6.dist-info/LICENSE
pykilosort-1.4.6.dist-info/METADATA
pykilosort-1.4.6.dist-info/WHEEL
pykilosort-1.4.6.dist-info/entry_points.txt
pykilosort-1.4.6.dist-info/top_level.txt
pykilosort-1.4.6.dist-info/RECORD
