Metadata-Version: 2.1
Name: pykilosort
Version: 1.4.6
Summary: Python port of KiloSort 2
Home-page: https://github.com/rossant/pykilosort
Author: Cyrille Rossant
Author-email: cyrille.rossant@gmail.com
License: BSD
Keywords: kilosort,spike sorting,electrophysiology,neuroscience
Classifier: Development Status :: 4 - Beta
Classifier: Intended Audience :: Developers
Classifier: License :: OSI Approved :: BSD License
Classifier: Natural Language :: English
Classifier: Framework :: IPython
Classifier: Programming Language :: Python :: 3
Classifier: Programming Language :: Python :: 3.7
License-File: LICENSE
